redisea/__init__.py
redisea/redisea.py
redisea-1.2.34.data/scripts/redisea.py
redisea-1.2.34.dist-info/LICENSE
redisea-1.2.34.dist-info/METADATA
redisea-1.2.34.dist-info/WHEEL
redisea-1.2.34.dist-info/entry_points.txt
redisea-1.2.34.dist-info/top_level.txt
redisea-1.2.34.dist-info/RECORD
