Metadata-Version: 2.1
Name: redisea
Version: 1.2.34
Summary: RediSea is a Redis (in-memory database) communication framework used for dumping key/value information within the Redis server, real-time Redis database analysis, and much more.
Home-page: https://github.com/battleoverflow/RediSea
Author: battleoverflow
Classifier: Programming Language :: Python :: 3
Classifier: License :: OSI Approved :: MIT License
Classifier: Operating System :: OS Independent
Requires-Python: >=3.6
License-File: LICENSE
Requires-Dist: argparse
Requires-Dist: redis
Requires-Dist: prettytable
